{
   "type": "postgres",
   "host": "raja.db.elephantsql.com",
   "username": "olysrlev",
   "password": "U36A0g7EOJaHo_hpKFlMsKwgGthKiLeC",
   "database": "olysrlev",
   "synchronize": true,
   "logging": false,
   "entities": [
      "src/entity/**/*.ts"
   ],
   "migrations": [
      "src/migration/**/*.ts"
   ],
   "subscribers": [
      "src/subscriber/**/*.ts"
   ],
   "cli": {
      "entitiesDir": "src/entity",
      "migrationsDir": "src/migration",
      "subscribersDir": "src/subscriber"
   }
}